setup.py
vondrak/__init__.py
vondrak.egg-info/PKG-INFO
vondrak.egg-info/SOURCES.txt
vondrak.egg-info/dependency_links.txt
vondrak.egg-info/requires.txt
vondrak.egg-info/top_level.txt
vondrak/docs/api.rst
vondrak/docs/examples.rst
vondrak/docs/index.rst
vondrak/docs/installation.rst
vondrak/docs/introduction.rst
vondrak/tests/__init__.py
vondrak/tests/test_precession.py