Metadata-Version: 1.1
Name: vondrak
Version: 0.03
Summary: A Python implementation of Vondrák's long term precession model and Fortran code.
Home-page: https://github.com/digitalvapor/vondrak
Author: Tom Spalding
Author-email: tommycs@mail.sfsu.edu
License: Creative Commons Attribution-ShareAlike 4.0 International License
Download-URL: https://github.com/digitalvapor/vondrak/tarball/0.03
Keywords: astronomy,precession,vondrak,space,proper motion
Platform: UNKNOWN
Classifier: Development Status :: 3 - Alpha
Classifier: Intended Audience :: Science/Research
Classifier: Programming Language :: Python
Classifier: Programming Language :: Python :: 2.6
Classifier: Programming Language :: Python :: 2.7
Classifier: Programming Language :: Python :: 3.2
Classifier: Programming Language :: Python :: 3.3
Classifier: Programming Language :: Python :: 3.4
Classifier: Topic :: Scientific/Engineering :: Astronomy
